shipzo_mult/__init__.py
shipzo_mult/mult.py
shipzo_mult_hun-0.1.0.dist-info/METADATA
shipzo_mult_hun-0.1.0.dist-info/WHEEL
shipzo_mult_hun-0.1.0.dist-info/entry_points.txt
shipzo_mult_hun-0.1.0.dist-info/top_level.txt
shipzo_mult_hun-0.1.0.dist-info/RECORD
